hanzo_net-0.1.20.dist-info/licenses/LICENSE
net/__init__.py
net/helpers.py
net/main.py
net/models.py
net/test_callbacks.py
net/api/__init__.py
net/api/chatgpt_api.py
net/apputil/__init__.py
net/apputil/anim.py
net/download/__init__.py
net/download/download_progress.py
net/download/new_shard_download.py
net/download/shard_download.py
net/download/test_new_shard_download.py
net/download/hf/__init__.py
net/download/hf/hf_helpers.py
net/inference/__init__.py
net/inference/debug_inference_engine.py
net/inference/dummy_inference_engine.py
net/inference/inference_engine.py
net/inference/shard.py
net/inference/test_dummy_inference_engine.py
net/inference/test_inference_engine.py
net/inference/tokenizers.py
net/inference/mlx/__init__.py
net/inference/mlx/losses.py
net/inference/mlx/sharded_inference_engine.py
net/inference/mlx/sharded_utils.py
net/inference/mlx/test_non_blocking.py
net/inference/mlx/test_sharded_model.py
net/inference/mlx/models/StableDiffusionPipeline.py
net/inference/mlx/models/__init__.py
net/inference/mlx/models/base.py
net/inference/mlx/models/deepseek_v2.py
net/inference/mlx/models/deepseek_v3.py
net/inference/mlx/models/gemma2.py
net/inference/mlx/models/llama.py
net/inference/mlx/models/llava.py
net/inference/mlx/models/phi3.py
net/inference/mlx/models/qwen2.py
net/inference/tinygrad/__init__.py
net/inference/tinygrad/inference.py
net/inference/tinygrad/losses.py
net/inference/tinygrad/stateful_model.py
net/inference/tinygrad/tinygrad_helpers.py
net/inference/tinygrad/models/__init__.py
net/inference/tinygrad/models/llama.py
net/netchat/common.css
net/netchat/favicon.ico
net/netchat/favicon.svg
net/netchat/index.css
net/netchat/index.html
net/netchat/index.js
net/netchat/update_deps.py
net/netchat/__pycache__/update_deps.cpython-312.pyc
net/netchat/static/cdn.jsdelivr.net/npm/@alpine-collective/toolkit@1.0.2/dist/cdn.min.js
net/netchat/static/cdn.jsdelivr.net/npm/@alpinejs/focus@3.x.x/dist/cdn.min.js
net/netchat/static/cdn.jsdelivr.net/npm/@alpinejs/intersect@3.x.x/dist/cdn.min.js
hanzo_net-0.1.20.dist-info/METADATA
hanzo_net-0.1.20.dist-info/WHEEL
hanzo_net-0.1.20.dist-info/entry_points.txt
hanzo_net-0.1.20.dist-info/top_level.txt
hanzo_net-0.1.20.dist-info/RECORD
